mavi_companion/__init__.py
mavi_companion/_tool.py
mavi_companion/agent.py
mavi_companion/main.py
mavi_companion-0.5.7.dist-info/METADATA
mavi_companion-0.5.7.dist-info/WHEEL
mavi_companion-0.5.7.dist-info/entry_points.txt
mavi_companion-0.5.7.dist-info/top_level.txt
mavi_companion-0.5.7.dist-info/RECORD
